[
  {
    "targetVertexWrapper": {
      "rootVertexId": null,
      "type": 463,
      "label": "PyTupleExpression"
    },
    "parentVertexWrapper": {
      "rootVertexId": 116,
      "type": 482,
      "label": "PyForPart"
    },
    "position": 0
  },
  {
    "targetVertexWrapper": {
      "rootVertexId": 1461,
      "type": 461,
      "label": "PyCallExpression: len"
    },
    "parentVertexWrapper": {
      "rootVertexId": 116,
      "type": 482,
      "label": "PyForPart"
    },
    "position": 1
  },
  {
    "targetVertexWrapper": {
      "rootVertexId": 1461,
      "type": 461,
      "label": "PyCallExpression: len"
    },
    "value": "PyCallExpression: enumerate"
  },
  {
    "targetVertexWrapper": {
      "rootVertexId": null,
      "type": 421,
      "label": "PyTargetExpression: i"
    },
    "parentVertexWrapper": {
      "rootVertexId": null,
      "type": 463,
      "label": "PyTupleExpression"
    },
    "position": 0
  },
  {
    "targetVertexWrapper": {
      "rootVertexId": null,
      "type": 421,
      "label": "PyTargetExpression: dim"
    },
    "parentVertexWrapper": {
      "rootVertexId": null,
      "type": 463,
      "label": "PyTupleExpression"
    },
    "position": 1
  },
  {
    "targetVertexWrapper": {
      "rootVertexId": null,
      "type": 448,
      "label": "PyReferenceExpression: len"
    },
    "value": "PyReferenceExpression: enumerate"
  },
  {
    "targetVertexWrapper": {
      "rootVertexId": 122,
      "type": 421,
      "label": "PyTargetExpression: i"
    }
  },
  {
    "targetVertexWrapper": {
      "rootVertexId": null,
      "type": 448,
      "label": "PyReferenceExpression: range"
    }
  },
  {
    "targetVertexWrapper": {
      "rootVertexId": 120,
      "type": 422,
      "label": "PyArgumentList"
    }
  },
  {
    "targetVertexWrapper": {
      "rootVertexId": 1457,
      "type": 461,
      "label": "PyCallExpression: range"
    }
  },
  {
    "targetVertexWrapper": {
      "rootVertexId": 1460,
      "type": 421,
      "label": "PyTargetExpression: dim"
    }
  },
  {
    "targetVertexWrapper": {
      "rootVertexId": 129,
      "type": 448,
      "label": "PyReferenceExpression: static"
    }
  },
  {
    "targetVertexWrapper": {
      "rootVertexId": 130,
      "type": 448,
      "label": "PyReferenceExpression: i"
    }
  },
  {
    "targetVertexWrapper": {
      "rootVertexId": 1459,
      "type": 456,
      "label": "PySubscriptionExpression"
    }
  },
  {
    "targetVertexWrapper": {
      "rootVertexId": 1465,
      "type": 426,
      "label": "PyAssignmentStatement"
    }
  }
]